a_move_files_by_excel/__init__.py
a_move_files_by_excel/move_files_by_excel.py
a_move_files_by_excel-0.1.1.dist-info/licenses/LICENSE
a_move_files_by_excel-0.1.1.dist-info/METADATA
a_move_files_by_excel-0.1.1.dist-info/WHEEL
a_move_files_by_excel-0.1.1.dist-info/entry_points.txt
a_move_files_by_excel-0.1.1.dist-info/top_level.txt
a_move_files_by_excel-0.1.1.dist-info/RECORD
