Metadata-Version: 2.4
Name: a_move_files_by_excel
Version: 0.1.1
Summary: 极简批量移动文件脚本，支持Excel批量移动并保留原始路径结构，适合所有用户。
Home-page: 
Author: nighm
Author-email: nighm@sina.com
License: MIT
Classifier: Programming Language :: Python :: 3
Classifier: License :: OSI Approved :: MIT License
Classifier: Operating System :: OS Independent
Requires-Python: >=3.7
License-File: LICENSE
Requires-Dist: pandas>=1.5.0
Requires-Dist: openpyxl>=3.0.10
Requires-Dist: lxml==4.9.3
Requires-Dist: html5lib==1.1
Requires-Dist: beautifulsoup4>=4.11.0
Requires-Dist: PyYAML>=6.0
Dynamic: author
Dynamic: author-email
Dynamic: classifier
Dynamic: description
Dynamic: description-content-type
Dynamic: license
Dynamic: license-file
Dynamic: requires-dist
Dynamic: requires-python
Dynamic: summary
